{
  "run_date": "2026-02-12T12:23:50Z",
  "run_id": "21946390800",
  "total_prs_triaged": 2,
  "new_prs": 2,
  "re_triaged": 0,
  "results": [
    {
      "number": 15142,
      "title": "Add prototype pollution protection to parseJsonWithRepair with stack-based algorithm",
      "category": "bug",
      "subcategory": "security",
      "risk": "high",
      "priority": {
        "total": 95,
        "impact": 50,
        "urgency": 30,
        "quality": 15
      },
      "action": "fast_track",
      "ci_status": "pending",
      "files_changed": 7,
      "total_changes": 516,
      "created_at": "2026-02-12T11:53:27Z",
      "updated_at": "2026-02-12T12:20:29Z",
      "url": "https://github.com/github/gh-aw/pull/15142"
    },
    {
      "number": 15084,
      "title": "Add support for GITHUB_ACTOR environment variable and --validate-actor flag in mcp-server command",
      "category": "feature",
      "risk": "medium",
      "priority": {
        "total": 48,
        "impact": 30,
        "urgency": 8,
        "quality": 10
      },
      "action": "batch_review",
      "ci_status": "pending",
      "files_changed": 27,
      "total_changes": 399,
      "created_at": "2026-02-12T04:05:18Z",
      "updated_at": "2026-02-12T12:20:49Z",
      "url": "https://github.com/github/gh-aw/pull/15084"
    }
  ],
  "statistics": {
    "by_category": {
      "bug": 1,
      "feature": 1,
      "docs": 0,
      "test": 0,
      "formatting": 0,
      "refactor": 0,
      "chore": 0
    },
    "by_risk": {
      "low": 0,
      "medium": 1,
      "high": 1
    },
    "by_priority": {
      "high": 1,
      "medium": 1,
      "low": 0
    },
    "by_action": {
      "auto_merge": 0,
      "fast_track": 1,
      "batch_review": 1,
      "defer": 0,
      "close": 0
    }
  },
  "auto_merge_candidates": [],
  "fast_track_needed": [15142],
  "batch_review_candidates": [15084],
  "defer_candidates": [],
  "close_candidates": [],
  "batches": {}
}
